<?xml version="1.0" encoding="utf-8" ?>

<percentile>
  <object>
        <lower>1</lower>
        <content>Lamia/1</content>
        <upper>4</upper>
    </object>
  <object>
    <lower>5</lower>
    <content>Annis (hag)/1</content>
    <upper>8</upper>
  </object>
  <object>
    <lower>9</lower>
    <content>Beholder/1</content>
    <upper>12</upper>
  </object>
  <object>
    <lower>13</lower>
    <content>Ogre/1d3+1</content>
    <upper>16</upper>
  </object>
  <object>
    <lower>17</lower>
    <content>Wererat/1d3+1,Dire rat/1d6+3</content>
    <upper>20</upper>
  </object>
  <object>
    <lower>21</lower>
    <content>Gargantuan monstrous centipede/1</content>
    <upper>24</upper>
  </object>
  <object>
    <lower>25</lower>
    <content>Cockatrice/1d3+1</content>
    <upper>28</upper>
  </object>
  <object>
    <lower>29</lower>
    <content>Digester/1</content>
    <upper>32</upper>
  </object>
  <object>
    <lower>33</lower>
    <content>Manticore/1d2</content>
    <upper>36</upper>
  </object>
  <object>
    <lower>37</lower>
    <content>Large monstrous scorpion/1d3+1</content>
    <upper>40</upper>
  </object>
  <object>
    <lower>41</lower>
    <content>Giant wasp/1d3+1</content>
    <upper>44</upper>
  </object>
  <object>
    <lower>45</lower>
    <content>Juvenile arrowhawk/1d3+1</content>
    <upper>46</upper>
  </object>
  <object>
    <lower>47</lower>
    <content>Barbazu (devil)/1d2</content>
    <upper>48</upper>
  </object>
  <object>
    <lower>49</lower>
    <content>Belker/1</content>
    <upper>50</upper>
  </object>
    <object>
        <lower>51</lower>
        <content>Formian warrior/1d3+1</content>
        <upper>52</upper>
    </object>
  <object>
    <lower>53</lower>
    <content>Howler/1d3+1</content>
    <upper>54</upper>
  </object>
  <object>
    <lower>55</lower>
    <content>Kyton (devil)/1</content>
    <upper>56</upper>
  </object>
  <object>
    <lower>57</lower>
    <content>Magmin/1d3+1</content>
    <upper>58</upper>
  </object>
    <object>
        <lower>59</lower>
        <content>Mephit/1d3+1</content>
        <upper>60</upper>
    </object>
  <object>
    <lower>61</lower>
    <content>Flamebrother salamander/1d3+1</content>
    <upper>62</upper>
  </object>
  <object>
    <lower>63</lower>
    <content>Average salamander/1</content>
    <upper>64</upper>
  </object>
  <object>
    <lower>65</lower>
    <content>Shadow/1d3+1</content>
    <upper>66</upper>
  </object>
  <object>
    <lower>67</lower>
    <content>Shadow mastiff/1d2</content>
    <upper>68</upper>
  </object>
  <object>
    <lower>69</lower>
    <content>Xill/1</content>
    <upper>70</upper>
  </object>
  <object>
    <lower>71</lower>
    <content>Minor xorn/1d3+1</content>
    <upper>72</upper>
  </object>
  <object>
    <lower>73</lower>
    <content>Average xorn/1</content>
    <upper>74</upper>
  </object>
  <object>
    <lower>75</lower>
    <content>Dragon/1</content>
    <upper>78</upper>
  </object>
    <object>
      <lower>79</lower>
        <content>Skeleton/1</content>
        <upper>80</upper>
    </object>
  <object>
    <lower>81</lower>
    <content>Zombie/1</content>
    <upper>82</upper>
  </object>
  <object>
    <lower>83</lower>
    <content>Celestial creature/1</content>
    <upper>84</upper>
  </object>
  <object>
    <lower>85</lower>
    <content>Fiendish creature/1</content>
    <upper>86</upper>
  </object>
  <object>
    <lower>87</lower>
    <content>Ravid/1,Tiny animated object/1d4+2</content>
    <upper>88</upper>
  </object>
  <object>
    <lower>89</lower>
    <content>Ravid/1,Small animated object/1d2</content>
    <upper>90</upper>
  </object>
  <object>
    <lower>91</lower>
    <content>Ravid/1,Medium animated object/1</content>
    <upper>92</upper>
  </object>
  <object>
    <lower>93</lower>
    <content>Ravid/1,Large animated object/1</content>
    <upper>94</upper>
  </object>
  <object>
    <lower>95</lower>
    <content>Character[3]/1d3+1</content>
    <upper>100</upper>
  </object>
</percentile>