<?xml version="1.0" encoding="utf-8" ?>

<percentile>
  <object>
        <lower>1</lower>
        <content>Barghest/1</content>
        <upper>2</upper>
    </object>
  <object>
    <lower>3</lower>
    <content>Dire rat/1d4+10</content>
    <upper>8</upper>
  </object>
  <object>
    <lower>9</lower>
    <content>Doppelganger/1d2</content>
    <upper>14</upper>
  </object>
  <object>
    <lower>15</lower>
    <content>Gargoyle/1</content>
    <upper>20</upper>
  </object>
  <object>
    <lower>21</lower>
    <content>Giant eagle/1d2</content>
    <upper>26</upper>
  </object>
  <object>
    <lower>27</lower>
    <content>Giant owl/1d2</content>
    <upper>32</upper>
  </object>
  <object>
    <lower>33</lower>
    <content>Hell hound/1d2</content>
    <upper>34</upper>
  </object>
  <object>
    <lower>35</lower>
    <content>Hound archon/1</content>
    <upper>36</upper>
  </object>
  <object>
    <lower>37</lower>
    <content>Janni/1</content>
    <upper>38</upper>
  </object>
  <object>
    <lower>39</lower>
    <content>Mimic/1</content>
    <upper>44</upper>
  </object>
    <object>
        <lower>45</lower>
        <content>Ogre/1d2</content>
        <upper>50</upper>
    </object>
  <object>
    <lower>51</lower>
    <content>Polar bear/1</content>
    <upper>56</upper>
  </object>
  <object>
    <lower>57</lower>
    <content>Flamebrother salamander/1d2</content>
    <upper>58</upper>
  </object>
  <object>
    <lower>59</lower>
    <content>Tiger/1d2</content>
    <upper>64</upper>
  </object>
  <object>
    <lower>65</lower>
    <content>Werewolf/1d2</content>
    <upper>70</upper>
  </object>
  <object>
    <lower>71</lower>
    <content>Wight/1d2</content>
    <upper>72</upper>
  </object>
  <object>
    <lower>73</lower>
    <content>Minor xorn/1d2</content>
    <upper>74</upper>
  </object>
    <object>
      <lower>75</lower>
        <content>Yeth hound/1d2</content>
        <upper>76</upper>
    </object>
  <object>
    <lower>77</lower>
    <content>Dragon/1</content>
    <upper>82</upper>
  </object>
  <object>
    <lower>83</lower>
    <content>Celestial creature/1</content>
    <upper>84</upper>
  </object>
    <object>
        <lower>85</lower>
        <content>Fiendish creature/1</content>
        <upper>86</upper>
    </object>
  <object>
    <lower>87</lower>
    <content>Skeleton/1</content>
    <upper>88</upper>
  </object>
  <object>
    <lower>89</lower>
    <content>Zombie/1</content>
    <upper>90</upper>
  </object>
  <object>
    <lower>91</lower>
    <content>Character[2]/1d3</content>
    <upper>100</upper>
  </object>
</percentile>